[
  {
    "id": 4603,
    "slug": "1-square",
    "title": "1 Square",
    "description": "1 Square is a jumping puzzle game. Jump from square to square, decrease the value of each to 1, then jump again to eliminate it. But don’t fall or get caught by the liquid! Clear all the squares and unlock the next challenge.",
    "instructions": "Controls: AD or left and right arrow keys = move (keep pressed for a continuous move) R = restart",
    "thumbnail": "https://img.gamedistribution.com/1a3a81cf3a784217b169479ff9b0bfbc-512x384.jpeg",
    "iframe_src": "https://html5.gamedistribution.com/1a3a81cf3a784217b169479ff9b0bfbc/?gd_sdk_referrer_url=https://www.example.com/games/{game-path}",
    "iframe_width": 1280,
    "iframe_height": 720,
    "primary_category": "arcade",
    "all_categories": [
      "agility"
    ],
    "tags": [
      "jumping",
      "number",
      "platformer"
    ],
    "devices": [
      "desktop",
      "mobile",
      "tablet"
    ],
    "developer": "Misc.261 Games",
    "batch_number": 18,
    "collection_time": "2025-06-09T21:59:41.321872",
    "featured": false
  },
  {
    "id": 4602,
    "slug": "gravity-soccer-3",
    "title": "Gravity Soccer 3",
    "description": "Solve all Gravity Soccer levels using logic. Destroy blocks and manage to get the ball into the net, trying to get all stars. Touch/Click the objects to destroy.",
    "instructions": "Touch/Click the objects to destroy.",
    "thumbnail": "https://img.gamedistribution.com/b85c6340b9bf4e84b6977d569e3499c5-512x384.jpeg",
    "iframe_src": "https://html5.gamedistribution.com/b85c6340b9bf4e84b6977d569e3499c5/?gd_sdk_referrer_url=https://www.example.com/games/{game-path}",
    "iframe_width": 720,
    "iframe_height": 405,
    "primary_category": "arcade",
    "all_categories": [
      "football"
    ],
    "tags": [
      "avoid",
      "ball",
      "ballblaster"
    ],
    "devices": [
      "desktop",
      "mobile",
      "tablet"
    ],
    "developer": "QkyGames",
    "batch_number": 18,
    "collection_time": "2025-06-09T21:59:41.353751",
    "featured": false
  },
  {
    "id": 4598,
    "slug": "tic-tac-toe-master",
    "title": "Tic Tac Toe Master",
    "description": "Tic Tac Toe Master is a skill game where 2 player game in which the objective is to take turns and mark the correct spaces, play against computer or against a friend. Challenge yourself from a traditional 3 X 3 grid, or custom board size from 5×5 to 8×8.",
    "instructions": "Use mouse on desktop or touch on your mobile device.",
    "thumbnail": "https://img.gamedistribution.com/28ca14de47374a79adfb2a64460f6219-512x384.jpeg",
    "iframe_src": "https://html5.gamedistribution.com/28ca14de47374a79adfb2a64460f6219/?gd_sdk_referrer_url=https://www.example.com/games/{game-path}",
    "iframe_width": 1280,
    "iframe_height": 768,
    "primary_category": "arcade",
    "all_categories": [
      "boardgames"
    ],
    "tags": [
      "co-op",
      "logic",
      "skill",
      "tictactoe"
    ],
    "devices": [
      "desktop",
      "mobile",
      "tablet"
    ],
    "developer": "Fun Best Games",
    "batch_number": 18,
    "collection_time": "2025-06-09T21:59:48.088777",
    "featured": false
  },
  {
    "id": 4595,
    "slug": "fun-memory-training",
    "title": "Fun Memory Training",
    "description": "Play Fun Memory Training online for free.  game.",
    "instructions": "Click or tap to play",
    "thumbnail": "",
    "iframe_src": "",
    "iframe_width": 800,
    "iframe_height": 600,
    "primary_category": "arcade",
    "all_categories": [],
    "tags": [],
    "devices": [
      "desktop"
    ],
    "developer": "未知开发商",
    "batch_number": 18,
    "collection_time": "2025-06-09T21:59:48.599066",
    "featured": false
  },
  {
    "id": 4594,
    "slug": "guess-my-sketch",
    "title": "Guess My Sketch",
    "description": "Play Guess My Sketch online for free.  game.",
    "instructions": "Click or tap to play",
    "thumbnail": "",
    "iframe_src": "",
    "iframe_width": 800,
    "iframe_height": 600,
    "primary_category": "arcade",
    "all_categories": [],
    "tags": [],
    "devices": [
      "desktop"
    ],
    "developer": "未知开发商",
    "batch_number": 18,
    "collection_time": "2025-06-09T21:59:48.541327",
    "featured": false
  },
  {
    "id": 4593,
    "slug": "gunfighter-gunmans-proof",
    "title": "Gunfighter Gunmans Proof",
    "description": "Play Gunfighter Gunmans Proof online for free.  game.",
    "instructions": "Click or tap to play",
    "thumbnail": "",
    "iframe_src": "",
    "iframe_width": 800,
    "iframe_height": 600,
    "primary_category": "arcade",
    "all_categories": [],
    "tags": [],
    "devices": [
      "desktop"
    ],
    "developer": "未知开发商",
    "batch_number": 18,
    "collection_time": "2025-06-09T21:59:48.470712",
    "featured": false
  },
  {
    "id": 4592,
    "slug": "space-killers-retro-edition",
    "title": "Space killers (Retro edition)",
    "description": "The war has begun. Aliens attacked the solar system. Fight with your space ship and shoot aliens. Use powerful weapons and defend the solar system against aliens. Get as many points as possible.",
    "instructions": "Use keyboard to control (arrows: left, down, right, up) and space to shot.",
    "thumbnail": "https://img.gamedistribution.com/fbe5fe978fc14d0688fd4db8b05b5688-512x384.jpeg",
    "iframe_src": "https://html5.gamedistribution.com/fbe5fe978fc14d0688fd4db8b05b5688/?gd_sdk_referrer_url=https://www.example.com/games/{game-path}",
    "iframe_width": 1024,
    "iframe_height": 768,
    "primary_category": "arcade",
    "all_categories": [
      "battle"
    ],
    "tags": [
      "1player",
      "airplane",
      "alien",
      "battleship",
      "challenge",
      "clicker",
      "highscore",
      "point-and-click",
      "retro",
      "rocket",
      "score",
      "ship",
      "singleplayer",
      "space",
      "spaceship",
      "warrior"
    ],
    "devices": [
      "desktop",
      "mobile",
      "tablet"
    ],
    "developer": "Airem",
    "batch_number": 18,
    "collection_time": "2025-06-09T21:59:48.353569",
    "featured": false
  },
  {
    "id": 4591,
    "slug": "aquapark-surfer-race",
    "title": "Aquapark Surfer Race",
    "description": "This game will simulate the thrill and joy of surfing! You will compete with multiple opponents in surfing on exciting sea slides. Avoid the swimming ring! Entering the acceleration zone can help you gain a short period of invincibility! Can you win the championship? Come and try!",
    "instructions": "Slide to move",
    "thumbnail": "https://img.gamedistribution.com/ce3af66d244645159af93801c82e3172-512x384.jpeg",
    "iframe_src": "https://html5.gamedistribution.com/ce3af66d244645159af93801c82e3172/?gd_sdk_referrer_url=https://www.example.com/games/{game-path}",
    "iframe_width": 750,
    "iframe_height": 1334,
    "primary_category": "arcade",
    "all_categories": [
      "racing & driving"
    ],
    "tags": [
      "avoid",
      "runner",
      "running",
      "water",
      "waterpark",
      "waterslide"
    ],
    "devices": [
      "desktop",
      "mobile",
      "tablet"
    ],
    "developer": "YAD.Com",
    "batch_number": 18,
    "collection_time": "2025-06-09T21:59:48.452219",
    "featured": false
  },
  {
    "id": 4589,
    "slug": "dotted-girl-new-era",
    "title": "Dotted Girl New Era",
    "description": "Meet the SuperHeroine in a new look! Today she is an ordinary girl who lives an everyday life, trying on modern outfits and dresses. Tomorrow she is a Superhero in a stylish jumpsuit and mask. Use a combination of different costume elements to create not only a unique hero, but also a SuperVillain! In addition, in this wonderful game, you can choose and design a cute helper.",
    "instructions": "Left mouse button or touch.",
    "thumbnail": "https://img.gamedistribution.com/e88a908ca8f64a57bc7dc81fcbd6c810-512x384.jpeg",
    "iframe_src": "https://html5.gamedistribution.com/e88a908ca8f64a57bc7dc81fcbd6c810/?gd_sdk_referrer_url=https://www.example.com/games/{game-path}",
    "iframe_width": 800,
    "iframe_height": 600,
    "primary_category": "arcade",
    "all_categories": [
      "dress-up"
    ],
    "tags": [
      "animal",
      "cute",
      "fashion",
      "hero",
      "princess"
    ],
    "devices": [
      "desktop",
      "mobile",
      "tablet"
    ],
    "developer": "DL-studio",
    "batch_number": 18,
    "collection_time": "2025-06-09T21:59:48.490154",
    "featured": false
  },
  {
    "id": 4587,
    "slug": "hugie-wugie-runner",
    "title": "Hugie Wugie Runner",
    "description": "If you like a sports game. This game is for you. Hugie Wugie runs away from people, but he needs to collect the battery to charge his power. The difficulty is always the hill of the mountain, he needs the best player to complete the work.",
    "instructions": "Press backward/forward to balance the bike. Press the up / down arrow key to move the bike.",
    "thumbnail": "https://img.gamedistribution.com/62305fd30cbf43169b3badf3513a55a4-512x512.jpeg",
    "iframe_src": "https://html5.gamedistribution.com/62305fd30cbf43169b3badf3513a55a4/?gd_sdk_referrer_url=https://www.example.com/games/{game-path}",
    "iframe_width": 1280,
    "iframe_height": 720,
    "primary_category": "arcade",
    "all_categories": [
      "racing & driving"
    ],
    "tags": [
      "bike",
      "biker",
      "mountain"
    ],
    "devices": [
      "desktop",
      "mobile",
      "tablet"
    ],
    "developer": "tegagame.com",
    "batch_number": 18,
    "collection_time": "2025-06-09T21:59:48.685623",
    "featured": false
  },
  {
    "id": 4586,
    "slug": "sky-stick",
    "title": "Sky Stick",
    "description": "Try to complete the course without getting stuck in obstacles in the fun track running race Sky Stick game. Do not fall into the gaps. The green parts will help you go fast, while the red parts will slow you down. It helps you bounce in the blue parts. We wish you a pleasant time in the game!",
    "instructions": "Left: Left Arrow Right: Right Arrow Jump: Up Arrow",
    "thumbnail": "https://img.gamedistribution.com/d7698dfcc92541b587d36626b84cd65f-512x384.jpeg",
    "iframe_src": "https://html5.gamedistribution.com/d7698dfcc92541b587d36626b84cd65f/?gd_sdk_referrer_url=https://www.example.com/games/{game-path}",
    "iframe_width": 800,
    "iframe_height": 450,
    "primary_category": "arcade",
    "all_categories": [
      "agility"
    ],
    "tags": [
      "1player",
      "3d",
      "run",
      "runner",
      "running",
      "singleplayer",
      "stickman"
    ],
    "devices": [
      "desktop",
      "mobile",
      "tablet"
    ],
    "developer": "Hihoy",
    "batch_number": 18,
    "collection_time": "2025-06-09T21:59:48.579459",
    "featured": false
  },
  {
    "id": 4584,
    "slug": "snake-io-war",
    "title": "Snake io war",
    "description": "Snake io war combines a new pop aesthetic with the oldest classic snake game mechanics.You love games with tons of real fun and dynamic action? Then welcome to the Snake io war, an awesome arcade, where you can become the great champion of the arena! Collect yummies and different powerups, defeat enemies, and become the biggest worm of them all!",
    "instructions": "Snake io war started with a snake and tried to eat something in each level to make it bigger. Twist your snake in the food pile and try to beat the scores of other players-how long can you survive?",
    "thumbnail": "https://img.gamedistribution.com/0d55ba42916343f1ac0ab38a47473dc0-512x384.jpeg",
    "iframe_src": "https://html5.gamedistribution.com/0d55ba42916343f1ac0ab38a47473dc0/?gd_sdk_referrer_url=https://www.example.com/games/{game-path}",
    "iframe_width": 1280,
    "iframe_height": 720,
    "primary_category": "arcade",
    "all_categories": [
      ".io"
    ],
    "tags": [
      "multiplayer",
      "snake",
      "war"
    ],
    "devices": [
      "desktop",
      "mobile",
      "tablet"
    ],
    "developer": "XTStudio",
    "batch_number": 18,
    "collection_time": "2025-06-09T21:59:48.558515",
    "featured": false
  },
  {
    "id": 4579,
    "slug": "minimal-bubble-shooter",
    "title": "Minimal Bubble Shooter",
    "description": "Click or touch where you want to shoot the bubble. Remove bubbles to create a cluster of 3 or more bubbles of the same color. The game ends if you let any bubble get past the line at the bottom of the screen.",
    "instructions": "Use mouse or touch pad to play this game.",
    "thumbnail": "https://img.gamedistribution.com/6dfa80eaf3ad46bb95dc18f2983c240d-512x384.jpeg",
    "iframe_src": "https://html5.gamedistribution.com/6dfa80eaf3ad46bb95dc18f2983c240d/?gd_sdk_referrer_url=https://www.example.com/games/{game-path}",
    "iframe_width": 720,
    "iframe_height": 1280,
    "primary_category": "arcade",
    "all_categories": [
      "bubble shooter"
    ],
    "tags": [],
    "devices": [
      "desktop",
      "mobile",
      "tablet"
    ],
    "developer": "Misc.261 Games",
    "batch_number": 18,
    "collection_time": "2025-06-09T21:59:48.719191",
    "featured": false
  },
  {
    "id": 4577,
    "slug": "tactical-princess",
    "title": "Tactical Princess",
    "description": "Holiday dedicated to the defenders of the Fatherland is approaching. The princesses decided to celebrate it with a paintball match. Train your memory and help the princesses collect equipment for the tournament. Which of the girls will become the most stylish tactical princess?",
    "instructions": "Left mouse button or touch.",
    "thumbnail": "https://img.gamedistribution.com/0b3ba39110264045930afee8284e83d6-512x384.jpeg",
    "iframe_src": "https://html5.gamedistribution.com/0b3ba39110264045930afee8284e83d6/?gd_sdk_referrer_url=https://www.example.com/games/{game-path}",
    "iframe_width": 800,
    "iframe_height": 600,
    "primary_category": "arcade",
    "all_categories": [
      "dress-up"
    ],
    "tags": [
      "holiday",
      "logic",
      "matching",
      "princess",
      "warrior",
      "weapons"
    ],
    "devices": [
      "desktop",
      "mobile",
      "tablet"
    ],
    "developer": "DL-studio",
    "batch_number": 18,
    "collection_time": "2025-06-09T21:59:48.782315",
    "featured": false
  },
  {
    "id": 4576,
    "slug": "knife-shooting",
    "title": "Knife Shooting",
    "description": "An action-packed fight awaits you with the Knife Shooting game. You have to hit all the targets by passing the challenging levels. You can buy yourself new knives with the apples in the levels.",
    "instructions": "It is played with the mouse.",
    "thumbnail": "https://img.gamedistribution.com/7b45129d1295434f8cccda6a3f937b33-512x384.jpeg",
    "iframe_src": "https://html5.gamedistribution.com/7b45129d1295434f8cccda6a3f937b33/?gd_sdk_referrer_url=https://www.example.com/games/{game-path}",
    "iframe_width": 440,
    "iframe_height": 750,
    "primary_category": "arcade",
    "all_categories": [
      "shooter"
    ],
    "tags": [
      "knife"
    ],
    "devices": [
      "desktop",
      "mobile",
      "tablet"
    ],
    "developer": "Rokito Games",
    "batch_number": 18,
    "collection_time": "2025-06-09T21:59:48.814179",
    "featured": false
  },
  {
    "id": 4575,
    "slug": "bird-trap",
    "title": "Bird trap",
    "description": "Make the little bird fly and don't touch the traps. How far can you make it? Also, earn coins and buy new birds in the shop. Enjoy atmospheric sounds and graphics.",
    "instructions": "Controls: mouse (left button), keyboard (space) or touch (mobile).",
    "thumbnail": "https://img.gamedistribution.com/b275ba9da5b64294900b56a094321095-512x384.jpeg",
    "iframe_src": "https://html5.gamedistribution.com/b275ba9da5b64294900b56a094321095/?gd_sdk_referrer_url=https://www.example.com/games/{game-path}",
    "iframe_width": 800,
    "iframe_height": 600,
    "primary_category": "arcade",
    "all_categories": [
      "agility"
    ],
    "tags": [
      "1player",
      "animal",
      "arcade",
      "arena",
      "bird",
      "challenge",
      "classic",
      "fall",
      "gravity",
      "hardcore",
      "old-school",
      "platformer",
      "retro",
      "singleplayer"
    ],
    "devices": [
      "desktop",
      "mobile",
      "tablet"
    ],
    "developer": "Airem",
    "batch_number": 18,
    "collection_time": "2025-06-09T21:59:48.766856",
    "featured": false
  },
  {
    "id": 4573,
    "slug": "frog-fights-with-buddies",
    "title": "Frog Fights With Buddies",
    "description": "Frogs! Jump from lily pad to lilypad, and eat bugs. Kick your frog opponents into the water! First to 15 points wins. Casual friendly frog theme with beautiful artwork.",
    "instructions": "Score 15 points to win in this PvP multiplayer game",
    "thumbnail": "https://img.gamedistribution.com/58623af68d8b40cba5148f9161f1f643-512x512.jpeg",
    "iframe_src": "https://html5.gamedistribution.com/58623af68d8b40cba5148f9161f1f643/?gd_sdk_referrer_url=https://www.example.com/games/{game-path}",
    "iframe_width": 1280,
    "iframe_height": 720,
    "primary_category": "arcade",
    "all_categories": [
      "battle"
    ],
    "tags": [
      "animal",
      "co-op",
      "family",
      "fighting",
      "multiplayer"
    ],
    "devices": [
      "desktop",
      "mobile",
      "tablet"
    ],
    "developer": "MarketJS",
    "batch_number": 18,
    "collection_time": "2025-06-09T21:59:55.580637",
    "featured": false
  },
  {
    "id": 4570,
    "slug": "garbage-rampage",
    "title": "Garbage Rampage",
    "description": "All you have to do is to drive, but not anyway, you have to clean the roads. Use your garbage truck to get as much junk as possible. While you drive your fuel will ultimately come up short, make a point to get fuel canisters that are dissipated en route.",
    "instructions": "Left / Right Keyboard Arrows or Left Mouse Click to Drive / Change direction",
    "thumbnail": "https://img.gamedistribution.com/396ef4a21f97424c83a053c97b3a070b-512x384.jpeg",
    "iframe_src": "https://html5.gamedistribution.com/396ef4a21f97424c83a053c97b3a070b/?gd_sdk_referrer_url=https://www.example.com/games/{game-path}",
    "iframe_width": 720,
    "iframe_height": 600,
    "primary_category": "arcade",
    "all_categories": [
      "agility"
    ],
    "tags": [
      "1player",
      "car",
      "collect",
      "endless",
      "singleplayer",
      "skill",
      "speed",
      "truck"
    ],
    "devices": [
      "desktop",
      "mobile",
      "tablet"
    ],
    "developer": "Vitalitygames.com",
    "batch_number": 18,
    "collection_time": "2025-06-09T21:59:48.895397",
    "featured": false
  },
  {
    "id": 4569,
    "slug": "squid-hook-game",
    "title": "Squid Hook Game",
    "description": "In Squid Hook Game, pull the Squid Game character on the opposite side to your side with the rope. Take advantage by sending the rope accurately to the other side. You can buy 5 different Squid game characters by accumulating the points you will earn at the end of each game. You can increase the action by purchasing dolls, players and workers. Grab your hook and fight against other players! Have fun.",
    "instructions": "Use mouse or touch pad to play this game.",
    "thumbnail": "https://img.gamedistribution.com/98689f34973441d6be22a417d26ee591-512x512.jpeg",
    "iframe_src": "https://html5.gamedistribution.com/98689f34973441d6be22a417d26ee591/?gd_sdk_referrer_url=https://www.example.com/games/{game-path}",
    "iframe_width": 800,
    "iframe_height": 600,
    "primary_category": "arcade",
    "all_categories": [
      ".io"
    ],
    "tags": [
      "arcade",
      "multiplayer"
    ],
    "devices": [
      "desktop",
      "mobile",
      "tablet"
    ],
    "developer": "Meyagames",
    "batch_number": 18,
    "collection_time": "2025-06-09T21:59:48.833456",
    "featured": false
  },
  {
    "id": 4568,
    "slug": "penalty-kick-wiz",
    "title": "Penalty Kick Wiz",
    "description": "Play Penalty Kick Wiz online for free. Football game.",
    "instructions": "To shoot: press anywhere and hold until the target is where you want to shoot. Then, release. To save: wait to see opponent's target, then tap on it. It's so easy to play! Football is a simple game, that's why we love it so much.",
    "thumbnail": "https://img.gamedistribution.com/64e48b1a1cd04510a8a6b287f4855e50-512x512.jpeg",
    "iframe_src": "https://html5.gamedistribution.com/64e48b1a1cd04510a8a6b287f4855e50/?gd_sdk_referrer_url=https://www.example.com/games/{game-path}",
    "iframe_width": 960,
    "iframe_height": 540,
    "primary_category": "arcade",
    "all_categories": [
      "football"
    ],
    "tags": [
      "champion",
      "penalty",
      "worldcup"
    ],
    "devices": [
      "desktop",
      "mobile",
      "tablet"
    ],
    "developer": "Physical Form",
    "batch_number": 18,
    "collection_time": "2025-06-09T21:59:48.874033",
    "featured": false
  },
  {
    "id": 4567,
    "slug": "red-stickman-fighting-stick",
    "title": "Red Stickman: Fighting Stick",
    "description": "Perfect news for the lovers of Red And Blue Stickman Animation! The sequel to the series has been completed and now available on mobile as Water and Fire: Forest Maze! The Forest Temple is an addictive platform puzzle game, where you have to control characters. Control both creatures at the same time and activate buttons to move platforms, push boxes and collect diamonds to get to the exit door of the forest temple?",
    "instructions": "How to play Red Stick Adventure : Animation vs Block Craft World - Move Red Stick by arrows and avoid obstacles. - Red boy must avoid the obstacle : water, enemy - Collect gems as many as possible Become a champion of a supreme stickman fight battle!",
    "thumbnail": "https://img.gamedistribution.com/f77966dc96794692b8ed9fdcf05a7ad3-512x384.jpg",
    "iframe_src": "https://html5.gamedistribution.com/f77966dc96794692b8ed9fdcf05a7ad3/?gd_sdk_referrer_url=https://www.example.com/games/{game-path}",
    "iframe_width": 960,
    "iframe_height": 600,
    "primary_category": "arcade",
    "all_categories": [
      "battle"
    ],
    "tags": [
      "2d",
      "levels",
      "platformer",
      "stickman",
      "sword"
    ],
    "devices": [
      "desktop",
      "mobile",
      "tablet"
    ],
    "developer": "Bin Studio",
    "batch_number": 18,
    "collection_time": "2025-06-09T21:59:48.853367",
    "featured": false
  },
  {
    "id": 4558,
    "slug": "hero-masters",
    "title": "Hero Masters",
    "description": "In our game you have to fight with different aliens. To defeat them, you have to become a real superhero. You will become available different superhero abilities as you go through the game. Each ability is strong in its own way, to win, you need to alternate them. Defeat all the aliens and save the world!",
    "instructions": "- Discover new abilities - Upgrade skills - alternate abilities - Defeat enemies - Use different skins",
    "thumbnail": "https://img.gamedistribution.com/cd027ed668ae48e79865312746dd9f0b-512x512.jpg",
    "iframe_src": "https://html5.gamedistribution.com/cd027ed668ae48e79865312746dd9f0b/?gd_sdk_referrer_url=https://www.example.com/games/{game-path}",
    "iframe_width": 800,
    "iframe_height": 600,
    "primary_category": "arcade",
    "all_categories": [
      "care"
    ],
    "tags": [
      "hero",
      "robot",
      "spiderman",
      "superhero"
    ],
    "devices": [
      "desktop",
      "mobile",
      "tablet"
    ],
    "developer": "Brosco Games",
    "batch_number": 18,
    "collection_time": "2025-06-09T21:59:55.897932",
    "featured": false
  },
  {
    "id": 4555,
    "slug": "riderio",
    "title": "Rider.io",
    "description": "Compete against other players in Rider.io and make insane jumps to challenge your opponents. Jump into your neon bike and win races to get your name to the TOP. Collect diamonds and Try different futuristic bikes on endless highways, upgrade your vehicle and be the fastest racer in this rapid rush!",
    "instructions": "Touch the screen or use the mouse to move",
    "thumbnail": "https://img.gamedistribution.com/571357d055374f078e471057d4fcdbea-512x384.jpeg",
    "iframe_src": "https://html5.gamedistribution.com/571357d055374f078e471057d4fcdbea/?gd_sdk_referrer_url=https://www.example.com/games/{game-path}",
    "iframe_width": 480,
    "iframe_height": 800,
    "primary_category": "arcade",
    "all_categories": [
      ".io"
    ],
    "tags": [
      "arcade",
      "bike",
      "rider"
    ],
    "devices": [
      "desktop",
      "mobile",
      "tablet"
    ],
    "developer": "kiz10.com",
    "batch_number": 18,
    "collection_time": "2025-06-09T21:59:56.143412",
    "featured": false
  },
  {
    "id": 4554,
    "slug": "professions",
    "title": "Professions",
    "description": "Professions Professions is a game developed for children in which they will learn the objects corresponding to each profession in a precise way from their mobile phone, tablet or computer. Game developed by: Nau.kids",
    "instructions": "Click on the objects corresponding to the profession.",
    "thumbnail": "https://img.gamedistribution.com/33406dac0eef403ba08150150dc7a9a3-512x512.jpeg",
    "iframe_src": "https://html5.gamedistribution.com/33406dac0eef403ba08150150dc7a9a3/?gd_sdk_referrer_url=https://www.example.com/games/{game-path}",
    "iframe_width": 800,
    "iframe_height": 450,
    "primary_category": "arcade",
    "all_categories": [
      "educational"
    ],
    "tags": [
      "preschool"
    ],
    "devices": [
      "desktop",
      "mobile",
      "tablet"
    ],
    "developer": "nau.kids",
    "batch_number": 18,
    "collection_time": "2025-06-09T21:59:56.101666",
    "featured": false
  },
  {
    "id": 4551,
    "slug": "real-extreme-car-driving-drift",
    "title": "Real Extreme Car Driving Drift",
    "description": "Real Extreme Car Driving Drift by Game Tap is ultimate car racing game with exciting new features. Extreme car simulator has advanced real physics engine so you get real car driving experience by playing this real car game.",
    "instructions": "USE W,A,S,D for player movement. Press F for nitrous",
    "thumbnail": "https://img.gamedistribution.com/cab69cd0d28c425b86c3d4c0a67693f1-512x384.jpeg",
    "iframe_src": "https://html5.gamedistribution.com/cab69cd0d28c425b86c3d4c0a67693f1/?gd_sdk_referrer_url=https://www.example.com/games/{game-path}",
    "iframe_width": 800,
    "iframe_height": 600,
    "primary_category": "arcade",
    "all_categories": [
      "racing & driving"
    ],
    "tags": [
      "3d"
    ],
    "devices": [
      "desktop",
      "mobile",
      "tablet"
    ],
    "developer": "Best Free Games",
    "batch_number": 18,
    "collection_time": "2025-06-09T21:59:56.118993",
    "featured": false
  },
  {
    "id": 4550,
    "slug": "eliza-winter-coronation",
    "title": "Eliza Winter Coronation",
    "description": "Princess Eliza assumes the throne this winter. She's getting ready to be queen. This is a very significant event for a girl. A princess must be irresistible at her coronation. Eliza's favorite season is winter, so the holiday will take place with the onset of cold weather. Let's travel to Eliza's magical ice kingdom and help her prepare for her coronation. First of all, you need to tidy up the skin, use care cosmetics to get rid of problems and imperfections on Eliza's face. Then comes the makeup. Pay attention to the fashion trends this winter, use shades of blue, white and gold. Then style the princess's hair in an evening hairstyle and match diamond jewelry. Finally, choose a luxurious ball gown and shoes for your coronation. You can also use magic accessories - capes and wings. Make Eliza's winter coronation a truly unique event in the entire Ice Kingdom!",
    "instructions": "Left mouse button or touch.",
    "thumbnail": "https://img.gamedistribution.com/93495d318d7b45c7a6e7868e4cc837c6-512x384.jpeg",
    "iframe_src": "https://html5.gamedistribution.com/93495d318d7b45c7a6e7868e4cc837c6/?gd_sdk_referrer_url=https://www.example.com/games/{game-path}",
    "iframe_width": 800,
    "iframe_height": 600,
    "primary_category": "arcade",
    "all_categories": [
      "dress-up"
    ],
    "tags": [
      "corona",
      "cute",
      "fashion",
      "holiday",
      "makeup",
      "princess",
      "winter"
    ],
    "devices": [
      "desktop",
      "mobile",
      "tablet"
    ],
    "developer": "DL-studio",
    "batch_number": 18,
    "collection_time": "2025-06-09T21:59:55.975615",
    "featured": false
  },
  {
    "id": 4549,
    "slug": "swipe-runner",
    "title": "Swipe Runner",
    "description": "This is a new race in which you have to choose a vehicle. Just swipe left to skip and swipe right to get an item. Can you get ahead of your opponent? Just try!",
    "instructions": "Swipe to change type of vehicle",
    "thumbnail": "https://img.gamedistribution.com/4a5d5f13b0d840b5a11b314cc469b176-512x384.jpeg",
    "iframe_src": "https://html5.gamedistribution.com/4a5d5f13b0d840b5a11b314cc469b176/?gd_sdk_referrer_url=https://www.example.com/games/{game-path}",
    "iframe_width": 360,
    "iframe_height": 640,
    "primary_category": "arcade",
    "all_categories": [
      ".io"
    ],
    "tags": [
      "3d",
      "multiplayer",
      "physics",
      "realistic",
      "runner",
      "running",
      "stickman"
    ],
    "devices": [
      "desktop",
      "mobile",
      "tablet"
    ],
    "developer": "Nevar Games",
    "batch_number": 18,
    "collection_time": "2025-06-09T21:59:56.163415",
    "featured": false
  },
  {
    "id": 4546,
    "slug": "yummy-donut-factory",
    "title": "Yummy Donut Factory",
    "description": "Let's be a donut chef! Mix all ingredients by following the receipt to make the dough. Create different shapes and bake the donuts. Decorate and throw on some sweet goodies, such as candies, sprinkles, frosting, and many more. You'll be the best donut baker ever!",
    "instructions": "Use MOUSE to play the game.",
    "thumbnail": "https://img.gamedistribution.com/d2d01e50efef4117895d07f85785bcd5-512x384.jpeg",
    "iframe_src": "https://html5.gamedistribution.com/d2d01e50efef4117895d07f85785bcd5/?gd_sdk_referrer_url=https://www.example.com/games/{game-path}",
    "iframe_width": 800,
    "iframe_height": 600,
    "primary_category": "arcade",
    "all_categories": [
      "cooking"
    ],
    "tags": [
      "cook"
    ],
    "devices": [
      "desktop",
      "mobile",
      "tablet"
    ],
    "developer": "iclickgames",
    "batch_number": 18,
    "collection_time": "2025-06-09T21:59:56.181874",
    "featured": false
  },
  {
    "id": 4544,
    "slug": "toon-drive-3d",
    "title": "Toon Drive 3D",
    "description": "Are you ready to experience a unique car driving gameplay? Start with your SUV and unlock new vehicles as you progress through the game, playing different and unique levels. Drive your favourite vehicles, and navigate your way around new challenging environments. We welcome all racing car game fans to experience this new driving game! Real Drive 3D is the best car simulation game of 2021 which will give you a unique arcade experience. Become a pro driver and master your parking skills in this new classic car simulator! Use your extreme stunt sports ability to navigate your way through a virtual multi story environment. Start with a 4x4, be it a Prado or an SUV, and get the ultimate driving school experience! Learn to park with a manual gear shift. Make sure not to crash or burnout - drive safely especially when you are driving offroad. Fasten your seat belt and unleash your inner racer by taking control of extreme vehicles in this parking mania. Challenge yourself with the rooftop levels or have fun in amusing virtual environments. Parking from one level to another has never been so much fun! The game features a wide selection of cars. Get ready to show your driving skills in this feature packed parking jam with multiple sedans, pickup truck, muscle car, some 4x4s, and – to top it off – many speedy supercars! GAME FEATURES - Modern hyper casual controls: Easy one finger control for a new and unique experience - Addictive controls: Hold to drive, release to brake - Portrait mode: For single handed gameplay - Vehicles include: Truck, Jeep, SUV, off-road vehicles, hyper cars, and an exclusive sports car",
    "instructions": "Use the steering wheel to control the car.",
    "thumbnail": "https://img.gamedistribution.com/787044f0c6964becba064c485f91f204-512x384.jpeg",
    "iframe_src": "https://html5.gamedistribution.com/787044f0c6964becba064c485f91f204/?gd_sdk_referrer_url=https://www.example.com/games/{game-path}",
    "iframe_width": 700,
    "iframe_height": 1100,
    "primary_category": "arcade",
    "all_categories": [
      "racing & driving"
    ],
    "tags": [
      "3d"
    ],
    "devices": [
      "desktop",
      "mobile",
      "tablet"
    ],
    "developer": "AyyHey",
    "batch_number": 18,
    "collection_time": "2025-06-09T21:59:56.218492",
    "featured": false
  },
  {
    "id": 4539,
    "slug": "bffs-trendy-squad-fashion",
    "title": "BFFs Trendy Squad Fashion",
    "description": "Welcome to the BFFs Trendy Squad Fashion. Barbie and her friends have a discussion on the weekend plan. And they come up with an idea to get ready for an upcoming fashion event. It’s a “Squad Fashion”. They all get excited to be show their fashion skill. Join and help the girls in preparation. Have fun!",
    "instructions": "Left Mouse Button Click",
    "thumbnail": "https://img.gamedistribution.com/1040d32b8f9d41f8bd75a94ab635f86f-512x384.jpeg",
    "iframe_src": "https://html5.gamedistribution.com/1040d32b8f9d41f8bd75a94ab635f86f/?gd_sdk_referrer_url=https://www.example.com/games/{game-path}",
    "iframe_width": 800,
    "iframe_height": 600,
    "primary_category": "arcade",
    "all_categories": [
      "dress-up"
    ],
    "tags": [
      "dressing",
      "fashion",
      "makeup"
    ],
    "devices": [
      "desktop",
      "mobile",
      "tablet"
    ],
    "developer": "Cutedressup",
    "batch_number": 18,
    "collection_time": "2025-06-09T21:59:56.301085",
    "featured": false
  },
  {
    "id": 4538,
    "slug": "mini-bubbles",
    "title": "Mini Bubbles",
    "description": "Play Mini Bubbles online for free.  game.",
    "instructions": "Click or tap to play",
    "thumbnail": "",
    "iframe_src": "",
    "iframe_width": 800,
    "iframe_height": 600,
    "primary_category": "arcade",
    "all_categories": [],
    "tags": [],
    "devices": [
      "desktop"
    ],
    "developer": "未知开发商",
    "batch_number": 19,
    "collection_time": "2025-06-09T22:00:33.014013",
    "featured": false
  },
  {
    "id": 4535,
    "slug": "tanks-pvp-showdown",
    "title": "Tanks PVP Showdown",
    "description": "Destroy your opponent's tank in this thrilling PvP real-time multiplayer game. Choose from a variety of weapons to deal massive damage to your enemies. Earn coins to unlock new tanks. Use emojis to taunt your opponents.",
    "instructions": "Select a weapon. Tap and drag to find a good shooting angle. Then, click on Fire",
    "thumbnail": "https://img.gamedistribution.com/17046ff8409849599b235afe908b4e58-512x512.jpeg",
    "iframe_src": "https://html5.gamedistribution.com/17046ff8409849599b235afe908b4e58/?gd_sdk_referrer_url=https://www.example.com/games/{game-path}",
    "iframe_width": 1280,
    "iframe_height": 720,
    "primary_category": "arcade",
    "all_categories": [
      ".io"
    ],
    "tags": [
      "co-op",
      "multiplayer"
    ],
    "devices": [
      "desktop",
      "mobile",
      "tablet"
    ],
    "developer": "MarketJS",
    "batch_number": 19,
    "collection_time": "2025-06-09T22:00:32.958456",
    "featured": false
  },
  {
    "id": 4534,
    "slug": "woodturning-studio",
    "title": "Woodturning Studio",
    "description": "In the Woodturning Studio game, sample wood is shaped with different wood carving knives. After wood carving, you can color the wood and apply varnish to it. Turn your imagination into wood art with this game. In the final scene, you can save your wood artwork to your phone / tablet gallery. Game Features; - Just swipe wood and create shapes - Unlimited combinations with different wood carving tools - Coloring, polishing and matting tools - You can save your artwork as an image.",
    "instructions": "Game played with MOUSE.",
    "thumbnail": "https://img.gamedistribution.com/d461e318e54740069fae8ac7886cc271-1280x720.jpeg",
    "iframe_src": "https://html5.gamedistribution.com/d461e318e54740069fae8ac7886cc271/?gd_sdk_referrer_url=https://www.example.com/games/{game-path}",
    "iframe_width": 800,
    "iframe_height": 450,
    "primary_category": "arcade",
    "all_categories": [
      "battle"
    ],
    "tags": [
      "design",
      "relaxing",
      "wood"
    ],
    "devices": [
      "desktop",
      "mobile",
      "tablet"
    ],
    "developer": "RHM Interactive",
    "batch_number": 19,
    "collection_time": "2025-06-09T22:00:33.051660",
    "featured": false
  },
  {
    "id": 4533,
    "slug": "papas-cupcakes-cooking-games",
    "title": "Papas Cupcakes Cooking Games",
    "description": "The rumor has it, your Cupcake Parlour is the best in town. New customers are coming in everyday and you need to keep it up to grow your business. Some orders are very specific and customized. Others will let your creativity get loose. You will be faced with new challenges everyday. The number one goal remain the same: complete each order in a predefined amount of time. As you complete each challenge, you will earn coins which will let you expand your business.",
    "instructions": "Hello kids we know you love to eat tasty creamy cupcake then why not try to bake your own cupcake in the fun dessert bakery shop. This cupcake baking games also have another surprise for little chef. Yes! this cupcake maker baking kitchen will going to teach the kids how to bake cupcakes in the lovely shape of unicorn.",
    "thumbnail": "https://img.gamedistribution.com/b416a34ed4d54c4e83f6ef82c6cf5413-512x384.jpeg",
    "iframe_src": "https://html5.gamedistribution.com/b416a34ed4d54c4e83f6ef82c6cf5413/?gd_sdk_referrer_url=https://www.example.com/games/{game-path}",
    "iframe_width": 960,
    "iframe_height": 640,
    "primary_category": "arcade",
    "all_categories": [
      "cooking"
    ],
    "tags": [
      "bake",
      "cake",
      "cupcake",
      "food"
    ],
    "devices": [
      "desktop",
      "mobile",
      "tablet"
    ],
    "developer": "BrillientGames",
    "batch_number": 19,
    "collection_time": "2025-06-09T22:00:32.913810",
    "featured": false
  },
  {
    "id": 4532,
    "slug": "march-coloring-book",
    "title": "March Coloring Book",
    "description": "Hello, young artist. Best season of the year is approaching - spring. This coloring-game is dedicated to the first month of spring - March. Flowers and cute animals will not leave anyone indifferent!",
    "instructions": "Left mouse button or touch.",
    "thumbnail": "https://img.gamedistribution.com/7f057afdf01d467db6f5873e660984ea-512x384.jpeg",
    "iframe_src": "https://html5.gamedistribution.com/7f057afdf01d467db6f5873e660984ea/?gd_sdk_referrer_url=https://www.example.com/games/{game-path}",
    "iframe_width": 800,
    "iframe_height": 600,
    "primary_category": "arcade",
    "all_categories": [
      "dress-up"
    ],
    "tags": [
      "animal",
      "coloring",
      "holiday",
      "spring"
    ],
    "devices": [
      "desktop",
      "mobile",
      "tablet"
    ],
    "developer": "DL-studio",
    "batch_number": 19,
    "collection_time": "2025-06-09T22:00:32.978028",
    "featured": false
  },
  {
    "id": 4531,
    "slug": "heels-stacky-rush-3d",
    "title": "Heels Stacky Rush 3D",
    "description": "Here is a running arcade game called Heels Stacky Rush 3D that offers you a chance to collect more heels and overpass block walls on sky platform tracks in a 3D skillful game. If you want to pass the blocks walls, you need to waste the same height of the heels as the current block wall. Keep calm and unlock your favorite skins in the shop!",
    "instructions": "Swipe to move left and right",
    "thumbnail": "https://img.gamedistribution.com/b9a43e272cc94ff2810a05a6679f044b-512x384.jpeg",
    "iframe_src": "https://html5.gamedistribution.com/b9a43e272cc94ff2810a05a6679f044b/?gd_sdk_referrer_url=https://www.example.com/games/{game-path}",
    "iframe_width": 750,
    "iframe_height": 1334,
    "primary_category": "arcade",
    "all_categories": [
      "agility"
    ],
    "tags": [
      "3d",
      "bomb",
      "platformer",
      "squidgame"
    ],
    "devices": [
      "desktop",
      "mobile",
      "tablet"
    ],
    "developer": "bestgames.com",
    "batch_number": 19,
    "collection_time": "2025-06-09T22:00:32.997545",
    "featured": false
  },
  {
    "id": 4525,
    "slug": "among-impostors",
    "title": "Among Impostors",
    "description": "In Among Impostors, you have to expand your team by eating the foods found around. In order to be stronger against your enemies, you can get stronger by taking the bonuses on the surface. If the number of your enemies is more than you, your enemies will become stronger by eating you. You can use the protective shield, speed shoes and impostor group bonus to collect the most Impostor. With the points you will earn at the end of the game, you can have new impostors or strengthen your existing character. You can play other impostor games for free at meyagames.com.",
    "instructions": "Use mouse or touch pad to play this game.",
    "thumbnail": "https://img.gamedistribution.com/def6fa6ebc9a47339d7bcf4fc18dcbab-512x384.jpeg",
    "iframe_src": "https://html5.gamedistribution.com/def6fa6ebc9a47339d7bcf4fc18dcbab/?gd_sdk_referrer_url=https://www.example.com/games/{game-path}",
    "iframe_width": 900,
    "iframe_height": 506,
    "primary_category": "arcade",
    "all_categories": [
      ".io"
    ],
    "tags": [
      "amongus",
      "arcade",
      "multiplayer"
    ],
    "devices": [
      "desktop",
      "mobile",
      "tablet"
    ],
    "developer": "Meyagames",
    "batch_number": 19,
    "collection_time": "2025-06-09T22:00:33.214820",
    "featured": false
  },
  {
    "id": 4523,
    "slug": "squid-gun-fest",
    "title": "Squid Gun Fest",
    "description": "Squid Game legend continues with Gun Fest game. Two of the most popular games of recent times are now gathered in one game. Gun Fest game is with you with Squid Game theme. Try to increase your weapons by doing math operations and destroy the Squid Game employees that you come across! The killer doll may appear sometimes and you must increase your weapon count as much as possible to destroy it. You have to shoot and destroy the obstacles in order to pass many obstacles. When you reach the final line, you can have the proceeds by destroying the robber car. You can buy new weapons with the money you earn. Start the game right away with endless levels and 6 different weapons. Have fun!",
    "instructions": "Use mouse or touch pad to play this game.",
    "thumbnail": "https://img.gamedistribution.com/78c1d094c2ec4a349da95f55567aa714-512x384.jpeg",
    "iframe_src": "https://html5.gamedistribution.com/78c1d094c2ec4a349da95f55567aa714/?gd_sdk_referrer_url=https://www.example.com/games/{game-path}",
    "iframe_width": 800,
    "iframe_height": 600,
    "primary_category": "arcade",
    "all_categories": [
      "shooter"
    ],
    "tags": [
      "3d",
      "arcade",
      "guns",
      "running",
      "weapons"
    ],
    "devices": [
      "desktop",
      "mobile",
      "tablet"
    ],
    "developer": "Meyagames",
    "batch_number": 19,
    "collection_time": "2025-06-09T22:00:33.173165",
    "featured": false
  },
  {
    "id": 4521,
    "slug": "fnaf-shooter",
    "title": "FNaF Shooter",
    "description": "Don't stay late at the supermarket! Cute funny animatronics come alive every night. They turn off the power and start hunting down the remaining visitors. You are the only one who can handle them. Animatronics are very tenacious, it is not enough to break their arm or leg, they will still haunt you. The only way to destroy them is to tear them apart. Survive and save the world from the invasion of animatronics!",
    "instructions": "Mouse - look around WASD - movement W + Shift - Run Left Mouse Button - Shoot Right Mouse Button (Hold) - Aim Mouse wheel - next/leading weapon 1-7 - weapon hotkeys R - reload F - knife attack G - throw a grenade T - inspect the weapon",
    "thumbnail": "https://img.gamedistribution.com/eb8346d4739e40eda6e4196dfc9166b7-512x384.jpeg",
    "iframe_src": "https://html5.gamedistribution.com/eb8346d4739e40eda6e4196dfc9166b7/?gd_sdk_referrer_url=https://www.example.com/games/{game-path}",
    "iframe_width": 800,
    "iframe_height": 600,
    "primary_category": "arcade",
    "all_categories": [
      "shooter"
    ],
    "tags": [
      "boys",
      "guns",
      "survival",
      "weapons"
    ],
    "devices": [
      "desktop",
      "mobile",
      "tablet"
    ],
    "developer": "GoGoMan",
    "batch_number": 19,
    "collection_time": "2025-06-09T22:00:33.155635",
    "featured": false
  },
  {
    "id": 4519,
    "slug": "labo-3d-maze",
    "title": "Labo 3D Maze",
    "description": "Try to pass 24 mazes with 5 different special characters. Avoid various traps and dangers... Collect keys to unlock doors and pass levels. Solve puzzles and reach the ultimate mystery...",
    "instructions": "Move: \"W,A,S,D\" Camera Angle: \"Mouse\" Zoom in / out: \"Mouse Scroll\" Interaction: \"E\"",
    "thumbnail": "https://img.gamedistribution.com/920024e0013244fab747ade7b7f5a60f-512x384.jpeg",
    "iframe_src": "https://html5.gamedistribution.com/920024e0013244fab747ade7b7f5a60f/?gd_sdk_referrer_url=https://www.example.com/games/{game-path}",
    "iframe_width": 800,
    "iframe_height": 450,
    "primary_category": "arcade",
    "all_categories": [
      "battle"
    ],
    "tags": [
      "3d",
      "collect",
      "escape"
    ],
    "devices": [
      "desktop",
      "mobile",
      "tablet"
    ],
    "developer": "RHM Interactive",
    "batch_number": 19,
    "collection_time": "2025-06-09T22:00:33.351016",
    "featured": false
  },
  {
    "id": 4517,
    "slug": "elon-cars-online-sky-stunt",
    "title": "Elon Cars : Online Sky Stunt",
    "description": "Elon Cars game series is a series with futuristic game ideas that you can play with pleasure. Let me quickly explain the first game of this series, Elon Cars: Online Sky Stunt series for you. As the name suggests, you can start the game by joining the empty game rooms in this game, which has a multiplayer game system. All you need for this will be 50 Elon Coins. Game rooms are for 5 people. After joining a game, each player starts the game with the same car. Our main goal in Elon Cars: Online Sky Stunt is to change our car by going across the map. With each car change, we will level 1 and the first player to reach Level 5 wins the game and some Elon Coins. It won't be as easy as you think. You have the right to fall from the map 3 times, don't forget that! Besides, you will be racing against time. The game is really hard. With the Elon Coins you earn, you can buy skins and tattoos for your car. You will love this game. Have fun !!",
    "instructions": "You can use the arrow keys of the keyboard for vehicle movement.",
    "thumbnail": "https://img.gamedistribution.com/63100a69f3e04d21b861748f1330a2e0-512x384.jpeg",
    "iframe_src": "https://html5.gamedistribution.com/63100a69f3e04d21b861748f1330a2e0/?gd_sdk_referrer_url=https://www.example.com/games/{game-path}",
    "iframe_width": 1280,
    "iframe_height": 720,
    "primary_category": "arcade",
    "all_categories": [
      ".io"
    ],
    "tags": [
      "car",
      "multiplayer",
      "space"
    ],
    "devices": [
      "desktop",
      "mobile",
      "tablet"
    ],
    "developer": "Xlab Game Studio",
    "batch_number": 19,
    "collection_time": "2025-06-09T22:00:33.434324",
    "featured": false
  },
  {
    "id": 4512,
    "slug": "dunkers-fight-2p",
    "title": "Dunkers Fight 2P",
    "description": "Get ready for basketball fun with the Dunkers Fight 2P game. Get ready when the countdown starts and grab the ball before your opponent. Try to throw your ball and hit the pot. If your opponent grabs the ball from your hand, resist him and protect the pot. Funny 2-person game your time playing with friends at school will pass with pleasure. Enjoy!",
    "instructions": "Player 1 Move: A-D Keys Player 1 Shoot: W-S Keys Player 2 Move: Left-Right Arrow Keys player 2 Shoot: Up-Down Arrow keys",
    "thumbnail": "https://img.gamedistribution.com/8a2140cdcb9a4e45a6545a692c36ca2a-512x512.jpeg",
    "iframe_src": "https://html5.gamedistribution.com/8a2140cdcb9a4e45a6545a692c36ca2a/?gd_sdk_referrer_url=https://www.example.com/games/{game-path}",
    "iframe_width": 800,
    "iframe_height": 450,
    "primary_category": "arcade",
    "all_categories": [
      "basketball"
    ],
    "tags": [
      "2players",
      "ball",
      "co-op",
      "dunk",
      "multiplayer",
      "sport"
    ],
    "devices": [
      "desktop",
      "mobile",
      "tablet"
    ],
    "developer": "Hihoy",
    "batch_number": 19,
    "collection_time": "2025-06-09T22:00:33.383719",
    "featured": false
  },
  {
    "id": 4511,
    "slug": "laser-cannon-2",
    "title": "Laser Cannon 2",
    "description": "Shoot, squash, blow up and destroy all the monsters in each level by using your laser cannon. Enjoy classic videogame now! The new “Laser Cannon” is bigger, better and more beautiful!",
    "instructions": "Use mouse to shot. Hold on the mouse button to Power shot. Use WASD or Arrows to move your cannon.",
    "thumbnail": "https://img.gamedistribution.com/8ffe97c318544b70a0247a30dcbdc654-512x384.jpeg",
    "iframe_src": "https://html5.gamedistribution.com/8ffe97c318544b70a0247a30dcbdc654/?gd_sdk_referrer_url=https://www.example.com/games/{game-path}",
    "iframe_width": 800,
    "iframe_height": 600,
    "primary_category": "arcade",
    "all_categories": [
      "battle"
    ],
    "tags": [
      "cannon",
      "fighting",
      "IceS",
      "monster"
    ],
    "devices": [
      "desktop",
      "mobile",
      "tablet"
    ],
    "developer": "HyperCarrot",
    "batch_number": 19,
    "collection_time": "2025-06-09T22:00:40.393296",
    "featured": false
  },
  {
    "id": 4510,
    "slug": "monsters-td-2",
    "title": "Monsters TD 2",
    "description": "Defend your base from a series of weird and freaky monsters. Build defenses to prevent them from reaching the portal. Monsters TD 2 is the sequel to the cool tower defense game and again you have to protect our world from little monsters. Build different towers to stop the creatures from reaching the portal to Earth. Your task is to pave the way with all kinds of towers to make it impossible for the monsters to pass.",
    "instructions": "Click, hold and drag the mouse cursor or WASD/arrow keys to move the screen. Use scroll wheel or key +/- to zoom / zoom out the screen. -1,2,3 – spells -space – speed up/ down -enter – start the wave",
    "thumbnail": "https://img.gamedistribution.com/6ffa9e52d3b64d55bd027be981928902-512x512.jpeg",
    "iframe_src": "https://html5.gamedistribution.com/6ffa9e52d3b64d55bd027be981928902/?gd_sdk_referrer_url=https://www.example.com/games/{game-path}",
    "iframe_width": 800,
    "iframe_height": 600,
    "primary_category": "arcade",
    "all_categories": [
      "battle"
    ],
    "tags": [
      "fighting",
      "IceS",
      "monster",
      "tower"
    ],
    "devices": [
      "desktop",
      "mobile",
      "tablet"
    ],
    "developer": "Booblyc OU",
    "batch_number": 19,
    "collection_time": "2025-06-09T22:00:40.456814",
    "featured": false
  },
  {
    "id": 4508,
    "slug": "impostor-warline-456-survivors",
    "title": "Impostor Warline 456 Survivors",
    "description": "Have fun with this new game Impostor Warline 456 Survivors an entertaining and exclusive game on kiz10.com !! On this occasion the little amons us who participated in a game like the squid game will try to win the first game but now armed Can you control this rebellion and eliminate all the participants who took up arms to eliminate and end the games? Have fun improving your characteristics and improve them by collecting gold and improving your score.",
    "instructions": "Instructions: Control the character on desktop with the mouse, shoot and use the items, keyboard arrows and keys W to go up and S to go down. Touch the screen on tablet and mobile devices.",
    "thumbnail": "https://img.gamedistribution.com/16feefe1e6114bcbb6ead5c0084f4b45-512x384.jpeg",
    "iframe_src": "https://html5.gamedistribution.com/16feefe1e6114bcbb6ead5c0084f4b45/?gd_sdk_referrer_url=https://www.example.com/games/{game-path}",
    "iframe_width": 800,
    "iframe_height": 600,
    "primary_category": "arcade",
    "all_categories": [
      "agility"
    ],
    "tags": [
      "amongus",
      "runner"
    ],
    "devices": [
      "desktop",
      "mobile",
      "tablet"
    ],
    "developer": "TapTapking.com",
    "batch_number": 19,
    "collection_time": "2025-06-09T22:00:33.399399",
    "featured": false
  },
  {
    "id": 4507,
    "slug": "penguin-cookshop",
    "title": "Penguin Cookshop",
    "description": "Penguins are clearly great entrepreneurs. And if this family of restaurant managers and chefs is any indication of how fast they can serve their customers, then this little diner is sure to thrive. Be quick and take the customers orders as fast as you can to get money, upgrades, and complete each level.",
    "instructions": "mouse/touchscreen",
    "thumbnail": "https://img.gamedistribution.com/79e0cbe5155c4e36945cd750e4013e52-512x384.jpeg",
    "iframe_src": "https://html5.gamedistribution.com/79e0cbe5155c4e36945cd750e4013e52/?gd_sdk_referrer_url=https://www.example.com/games/{game-path}",
    "iframe_width": 800,
    "iframe_height": 600,
    "primary_category": "arcade",
    "all_categories": [
      "cooking"
    ],
    "tags": [
      "cook",
      "IceS"
    ],
    "devices": [
      "desktop",
      "mobile",
      "tablet"
    ],
    "developer": "funky forest",
    "batch_number": 19,
    "collection_time": "2025-06-09T22:00:33.514131",
    "featured": false
  },
  {
    "id": 4504,
    "slug": "laser-cannon-3",
    "title": "Laser Cannon 3",
    "description": "The new game in “Laser Cannon” series. New locations, new monsters, new gear. Kill’em all! Laser Cannon 3 is finally back and now the funny physics-based shooting game goes into the third round. It's up to you to save our planet one more time against a bunch of annoying alien creatures. Clear each stage using your mighty cannon and try to shoot them all with as less shots as possible.",
    "instructions": "The fewer shots you need, the better. So aim well before you fire and make sure that every shot is a hit. These strange creatures must be destroyed, and you are the only person who can do it. Are you ready for this responsible task? Find out now and have fun with Laser Cannon 3! Controls: Mouse = Aim / Shoot",
    "thumbnail": "https://img.gamedistribution.com/b02d2e71e5ea45aca38dc93960acdc04-512x512.jpeg",
    "iframe_src": "https://html5.gamedistribution.com/b02d2e71e5ea45aca38dc93960acdc04/?gd_sdk_referrer_url=https://www.example.com/games/{game-path}",
    "iframe_width": 800,
    "iframe_height": 600,
    "primary_category": "arcade",
    "all_categories": [
      "battle"
    ],
    "tags": [
      "fighting",
      "IceS"
    ],
    "devices": [
      "desktop",
      "mobile",
      "tablet"
    ],
    "developer": "HyperCarrot",
    "batch_number": 19,
    "collection_time": "2025-06-09T22:00:40.418792",
    "featured": false
  },
  {
    "id": 4499,
    "slug": "thrilling-snow-motor",
    "title": "Thrilling Snow Motor",
    "description": "Here is a snow motorbike driving simulation game called Thrilling Snow Motor, which is a 3D game. It is managed for you to drive the motor to the finish line while collecting gold coins. Be aware of overpassing the interspaces in the platforms. If you control the wheel when you leave the ramp, your motor will fall and the game will lose directly. Good luck and unlock more skins!",
    "instructions": "WASD - move",
    "thumbnail": "https://img.gamedistribution.com/7802447ae6a7442a9fd5b2dee8ab58a4-512x384.jpeg",
    "iframe_src": "https://html5.gamedistribution.com/7802447ae6a7442a9fd5b2dee8ab58a4/?gd_sdk_referrer_url=https://www.example.com/games/{game-path}",
    "iframe_width": 1334,
    "iframe_height": 750,
    "primary_category": "arcade",
    "all_categories": [
      "agility"
    ],
    "tags": [
      "3d",
      "collect",
      "motorcycle",
      "platformer"
    ],
    "devices": [
      "desktop",
      "mobile",
      "tablet"
    ],
    "developer": "CarGames.Com",
    "batch_number": 19,
    "collection_time": "2025-06-09T22:00:40.738837",
    "featured": false
  },
  {
    "id": 4498,
    "slug": "mad-burger-2",
    "title": "Mad Burger 2",
    "description": "Mad burger is back! Launch the hot burger as far as possible, new upgrades, bonuses and lots of features included! Enjoy good-quality launcher game and have fun!",
    "instructions": "touchscreen/mouse+keyboard",
    "thumbnail": "https://img.gamedistribution.com/474483c765e846a9996164428342ab07-512x384.jpeg",
    "iframe_src": "https://html5.gamedistribution.com/474483c765e846a9996164428342ab07/?gd_sdk_referrer_url=https://www.example.com/games/{game-path}",
    "iframe_width": 800,
    "iframe_height": 600,
    "primary_category": "arcade",
    "all_categories": [
      "cooking"
    ],
    "tags": [
      "burger",
      "classic",
      "hamburger",
      "IceS"
    ],
    "devices": [
      "desktop",
      "mobile",
      "tablet"
    ],
    "developer": "Flash From The Past",
    "batch_number": 19,
    "collection_time": "2025-06-09T22:00:40.721276",
    "featured": false
  },
  {
    "id": 4495,
    "slug": "sarens",
    "title": "Sarens",
    "description": "The enemy reached the Sarens valley. Defending the survivors, you will plunge into intense battles. Battling for one of the spirits of elements you will have different magic and abilities. You will get awards for the victory. It is also possible to try yourself in more complicated modes. On the enemy side – magic power, different weapon attacks and golems. On your side there are three great elements of Ice, Fire and Lightning. High-quality and stylish graphics create the right atmosphere of the game.",
    "instructions": "Controls: Mouse for all actions. Press the magic button at the right court to choose the magic, press it again to resume the game. Click on the stickmen to hit them.",
    "thumbnail": "https://img.gamedistribution.com/c21fb93debe54e968d5b926db71f3308-512x384.jpeg",
    "iframe_src": "https://html5.gamedistribution.com/c21fb93debe54e968d5b926db71f3308/?gd_sdk_referrer_url=https://www.example.com/games/{game-path}",
    "iframe_width": 800,
    "iframe_height": 600,
    "primary_category": "arcade",
    "all_categories": [
      "battle"
    ],
    "tags": [
      "battlefield",
      "top",
      "warrior"
    ],
    "devices": [
      "desktop",
      "mobile",
      "tablet"
    ],
    "developer": "Booblyc OU",
    "batch_number": 19,
    "collection_time": "2025-06-09T22:00:40.612874",
    "featured": false
  }
]